dagster_deltalake/__init__.py
dagster_deltalake/config.py
dagster_deltalake/handler.py
dagster_deltalake/io_manager.py
dagster_deltalake/py.typed
dagster_deltalake/resource.py
dagster_deltalake/version.py
dagster_deltalake-0.28.13.dist-info/licenses/LICENSE
dagster_deltalake-0.28.13.dist-info/METADATA
dagster_deltalake-0.28.13.dist-info/WHEEL
dagster_deltalake-0.28.13.dist-info/top_level.txt
dagster_deltalake-0.28.13.dist-info/RECORD
