Metadata-Version: 2.4
Name: dagster-deltalake
Version: 0.28.13
Summary: Package for Deltalake-specific Dagster framework op and resource components.
Home-page: https://github.com/dagster-io/dagster/tree/master/python_modules/libraries/dagster-deltalake
Author: Elementl
Author-email: hello@elementl.com
License: Apache-2.0
Classifier: Programming Language :: Python :: 3.10
Classifier: License :: OSI Approved :: Apache Software License
Classifier: Operating System :: OS Independent
Requires-Python: >=3.10,<3.15
License-File: LICENSE
Requires-Dist: deltalake>=1.0.0
Requires-Dist: pyarrow
Requires-Dist: dagster==1.12.13
Provides-Extra: pandas
Requires-Dist: pandas<3.0.0; extra == "pandas"
Dynamic: author
Dynamic: author-email
Dynamic: classifier
Dynamic: home-page
Dynamic: license
Dynamic: license-file
Dynamic: provides-extra
Dynamic: requires-dist
Dynamic: requires-python
Dynamic: summary
